<annotation>
  <folder>Stairs</folder>
  <filename>STR_S3_17</filename>
  <path>C:\Users\Glen\Desktop\proj CM\Stairs\STR_S3_17.JPG</path>
  <source>
    <database>Unknown</database>
  </source>
  <size>
    <width>3456</width>
    <height>4608</height>
    <depth>3</depth>
  </size>
  <segmented>0</segmented>
  <object>
    <name>staircase</name>
    <pose>Unspecified</pose>
    <truncated>0</truncated>
    <difficult>0</difficult>
    <bndbox>
      <xmin>177</xmin>
      <ymin>1750</ymin>
      <xmax>2424</xmax>
      <ymax>4477</ymax>
    </bndbox>
  </object>
  <object>
    <name>staircase</name>
    <pose>Unspecified</pose>
    <truncated>0</truncated>
    <difficult>0</difficult>
    <bndbox>
      <xmin>2144</xmin>
      <ymin>2017</ymin>
      <xmax>3456</xmax>
      <ymax>4007</ymax>
    </bndbox>
  </object>
</annotation>
